setup.cfg
setup.py
manuf/__init__.py
manuf/__main__.py
manuf/manuf
manuf/manuf.py
manuf_ng.egg-info/PKG-INFO
manuf_ng.egg-info/SOURCES.txt
manuf_ng.egg-info/dependency_links.txt
manuf_ng.egg-info/entry_points.txt
manuf_ng.egg-info/top_level.txt