Metadata-Version: 1.0
Name: manuf-ng
Version: 1.0.0
Summary: Parser library for Wireshark's OUI database
Home-page: https://github.com/daniel-leicht/manuf/
Author: Michael Huang and Daniel Leicht
Author-email: UNKNOWN
License: Apache License 2.0 or GPLv3
Keywords: manuf,manuf-ng,mac address,networking
Platform: UNKNOWN
